opa_client/__init__.py
opa_client/base.py
opa_client/errors.py
opa_client/opa.py
opa_client/opa_async.py
opa_client/test/__init__.py
opa_client/test/test_async_client.py
opa_client/test/test_integaration_opa.py
opa_client/test/test_opa.py
opa_client/test/test_opa_client.py
opa_python_client-2.0.3.dist-info/LICENCE.md
opa_python_client-2.0.3.dist-info/METADATA
opa_python_client-2.0.3.dist-info/WHEEL
opa_python_client-2.0.3.dist-info/RECORD
