Metadata-Version: 2.3
Name: opa-python-client
Version: 2.0.3
Summary: Client for connection to the OPA service
License: MIT
Author: Tural Muradov
Author-email: tural.muradoov@gmail.com
Requires-Python: >=3.9,<4.0
Classifier: Intended Audience :: Developers
Classifier: License :: OSI Approved :: MIT License
Classifier: Operating System :: OS Independent
Classifier: Programming Language :: Python
Classifier: Programming Language :: Python :: 3
Classifier: Programming Language :: Python :: 3.9
Classifier: Programming Language :: Python :: 3.10
Classifier: Programming Language :: Python :: 3.11
Classifier: Programming Language :: Python :: 3.12
Classifier: Programming Language :: Python :: 3.13
Classifier: Programming Language :: Python :: 3 :: Only
Requires-Dist: aiofiles (>=24.1.0,<25.0.0)
Requires-Dist: aiohttp[speedups] (>=3.10.9,<4.0.0)
Requires-Dist: requests (>=2.32.3,<3.0.0)
Requires-Dist: urllib3 (>=2.5.0,<3.0.0)
Project-URL: Homepage, https://github.com/Turall/OPA-python-client
Project-URL: Repository, https://github.com/Turall/OPA-python-client
